{
  "experiment": "gemma_2b_cognitive_nov20",
  "trait": "defensiveness",
  "n_layers": 26,
  "methods": [
    "mean_diff",
    "probe",
    "ica",
    "gradient"
  ],
  "quadrants": {
    "inst_inst": {
      "description": "Instruction \u2192 Instruction",
      "vector_source": "defensiveness",
      "test_source": "instruction",
      "methods": {
        "mean_diff": {
          "all_layers": [
            {
              "accuracy": 0.5076923076923077,
              "separation": 121.79016876220703,
              "pos_mean": 194.9437713623047,
              "neg_mean": 73.15360260009766,
              "pos_std": 66.66305541992188,
              "neg_std": 20.4542179107666,
              "layer": 0
            },
            {
              "accuracy": 0.5128205128205128,
              "separation": 183.49035263061523,
              "pos_mean": 243.65403747558594,
              "neg_mean": 60.1636848449707,
              "pos_std": 69.65502166748047,
              "neg_std": 31.623394012451172,
              "layer": 1
            },
            {
              "accuracy": 0.7435897435897436,
              "separation": 219.94077348709106,
              "pos_mean": 225.11761474609375,
              "neg_mean": 5.1768412590026855,
              "pos_std": 85.56277465820312,
              "neg_std": 36.20827102661133,
              "layer": 2
            },
            {
              "accuracy": 0.517948717948718,
              "separation": 270.49245834350586,
              "pos_mean": 322.27703857421875,
              "neg_mean": 51.78458023071289,
              "pos_std": 113.27120971679688,
              "neg_std": 42.80804443359375,
              "layer": 3
            },
            {
              "accuracy": 0.6871794871794872,
              "separation": 405.4270477294922,
              "pos_mean": 433.0007019042969,
              "neg_mean": 27.573654174804688,
              "pos_std": 183.40304565429688,
              "neg_std": 59.29816818237305,
              "layer": 4
            },
            {
              "accuracy": 0.5230769230769231,
              "separation": 606.2457275390625,
              "pos_mean": 716.2698364257812,
              "neg_mean": 110.02410888671875,
              "pos_std": 285.2351989746094,
              "neg_std": 83.71768188476562,
              "layer": 5
            },
            {
              "accuracy": 0.5076923076923077,
              "separation": 810.2561340332031,
              "pos_mean": 1220.491943359375,
              "neg_mean": 410.2358093261719,
              "pos_std": 455.1542053222656,
              "neg_std": 107.31605529785156,
              "layer": 6
            },
            {
              "accuracy": 0.5076923076923077,
              "separation": 1466.0283203125,
              "pos_mean": 2059.34521484375,
              "neg_mean": 593.31689453125,
              "pos_std": 734.7302856445312,
              "neg_std": 198.7576446533203,
              "layer": 7
            },
            {
              "accuracy": 0.5076923076923077,
              "separation": 1577.6503601074219,
              "pos_mean": 2083.6103515625,
              "neg_mean": 505.9599914550781,
              "pos_std": 752.5068359375,
              "neg_std": 212.8873748779297,
              "layer": 8
            },
            {
              "accuracy": 0.5076923076923077,
              "separation": 1747.2972412109375,
              "pos_mean": 2068.705078125,
              "neg_mean": 321.4078369140625,
              "pos_std": 792.1024169921875,
              "neg_std": 220.38645935058594,
              "layer": 9
            },
            {
              "accuracy": 0.5076923076923077,
              "separation": 2542.37109375,
              "pos_mean": 3628.98828125,
              "neg_mean": 1086.6171875,
              "pos_std": 1305.4658203125,
              "neg_std": 313.2529602050781,
              "layer": 10
            },
            {
              "accuracy": 0.5128205128205128,
              "separation": 2793.2498474121094,
              "pos_mean": 3258.973388671875,
              "neg_mean": 465.7235412597656,
              "pos_std": 1249.692626953125,
              "neg_std": 344.59417724609375,
              "layer": 11
            },
            {
              "accuracy": 0.5076923076923077,
              "separation": 3330.70068359375,
              "pos_mean": 4734.8154296875,
              "neg_mean": 1404.11474609375,
              "pos_std": 1664.4107666015625,
              "neg_std": 411.4785461425781,
              "layer": 12
            },
            {
              "accuracy": 0.5948717948717949,
              "separation": 4164.812255859375,
              "pos_mean": 4583.60498046875,
              "neg_mean": 418.792724609375,
              "pos_std": 1781.1842041015625,
              "neg_std": 518.9515991210938,
              "layer": 13
            },
            {
              "accuracy": 0.5076923076923077,
              "separation": 4719.10205078125,
              "pos_mean": 6473.28662109375,
              "neg_mean": 1754.1845703125,
              "pos_std": 2201.52001953125,
              "neg_std": 588.86376953125,
              "layer": 14
            },
            {
              "accuracy": 0.5076923076923077,
              "separation": 6353.444580078125,
              "pos_mean": 9029.04296875,
              "neg_mean": 2675.598388671875,
              "pos_std": 2803.925537109375,
              "neg_std": 792.4373779296875,
              "layer": 15
            },
            {
              "accuracy": 0.5076923076923077,
              "separation": 8473.832275390625,
              "pos_mean": 11848.7412109375,
              "neg_mean": 3374.908935546875,
              "pos_std": 3538.4443359375,
              "neg_std": 1084.7508544921875,
              "layer": 16
            },
            {
              "accuracy": 0.5076923076923077,
              "separation": 9454.8193359375,
              "pos_mean": 13674.849609375,
              "neg_mean": 4220.0302734375,
              "pos_std": 4026.92529296875,
              "neg_std": 1159.5972900390625,
              "layer": 17
            },
            {
              "accuracy": 0.5076923076923077,
              "separation": 11389.18115234375,
              "pos_mean": 16164.892578125,
              "neg_mean": 4775.71142578125,
              "pos_std": 4624.42822265625,
              "neg_std": 1503.623046875,
              "layer": 18
            },
            {
              "accuracy": 0.5076923076923077,
              "separation": 12682.68798828125,
              "pos_mean": 17827.181640625,
              "neg_mean": 5144.49365234375,
              "pos_std": 4864.634765625,
              "neg_std": 1732.818603515625,
              "layer": 19
            },
            {
              "accuracy": 0.5076923076923077,
              "separation": 14459.181640625,
              "pos_mean": 20404.232421875,
              "neg_mean": 5945.05078125,
              "pos_std": 5390.2080078125,
              "neg_std": 1976.094482421875,
              "layer": 20
            },
            {
              "accuracy": 0.5076923076923077,
              "separation": 19851.572265625,
              "pos_mean": 28091.29296875,
              "neg_mean": 8239.720703125,
              "pos_std": 6696.55517578125,
              "neg_std": 2859.374267578125,
              "layer": 21
            },
            {
              "accuracy": 0.5076923076923077,
              "separation": 22978.958984375,
              "pos_mean": 32020.2265625,
              "neg_mean": 9041.267578125,
              "pos_std": 7375.7861328125,
              "neg_std": 3356.934814453125,
              "layer": 22
            },
            {
              "accuracy": 0.5076923076923077,
              "separation": 26187.42578125,
              "pos_mean": 35888.55859375,
              "neg_mean": 9701.1328125,
              "pos_std": 7671.04052734375,
              "neg_std": 4056.812744140625,
              "layer": 23
            },
            {
              "accuracy": 0.5076923076923077,
              "separation": 39580.669921875,
              "pos_mean": 63333.56640625,
              "neg_mean": 23752.896484375,
              "pos_std": 10185.0576171875,
              "neg_std": 6039.57177734375,
              "layer": 24
            },
            {
              "accuracy": 0.5076923076923077,
              "separation": 103239.796875,
              "pos_mean": 276578.375,
              "neg_mean": 173338.578125,
              "pos_std": 25725.638671875,
              "neg_std": 19532.630859375,
              "layer": 25
            }
          ],
          "best_layer": 2,
          "best_accuracy": 0.7435897435897436,
          "best_separation": 219.94077348709106,
          "avg_accuracy": 0.5284023668639053
        },
        "probe": {
          "all_layers": [
            {
              "accuracy": 1.0,
              "separation": 13.248161315917969,
              "pos_mean": 7.242317199707031,
              "neg_mean": -6.0058441162109375,
              "pos_std": 2.7651681900024414,
              "neg_std": 1.6424236297607422,
              "layer": 0
            },
            {
              "accuracy": 1.0,
              "separation": 14.423712253570557,
              "pos_mean": 7.760824680328369,
              "neg_mean": -6.6628875732421875,
              "pos_std": 2.5945191383361816,
              "neg_std": 1.8322303295135498,
              "layer": 1
            },
            {
              "accuracy": 1.0,
              "separation": 15.367835521697998,
              "pos_mean": 8.48486042022705,
              "neg_mean": -6.882975101470947,
              "pos_std": 3.349961280822754,
              "neg_std": 1.941792368888855,
              "layer": 2
            },
            {
              "accuracy": 1.0,
              "separation": 15.637876987457275,
              "pos_mean": 8.711853981018066,
              "neg_mean": -6.926023006439209,
              "pos_std": 3.397895097732544,
              "neg_std": 1.9505890607833862,
              "layer": 3
            },
            {
              "accuracy": 1.0,
              "separation": 17.46738290786743,
              "pos_mean": 10.152233123779297,
              "neg_mean": -7.315149784088135,
              "pos_std": 4.56224250793457,
              "neg_std": 2.09122896194458,
              "layer": 4
            },
            {
              "accuracy": 1.0,
              "separation": 18.390395164489746,
              "pos_mean": 10.7883939743042,
              "neg_mean": -7.602001190185547,
              "pos_std": 4.396385669708252,
              "neg_std": 2.1196255683898926,
              "layer": 5
            },
            {
              "accuracy": 1.0,
              "separation": 18.834077835083008,
              "pos_mean": 11.220434188842773,
              "neg_mean": -7.613643646240234,
              "pos_std": 4.560360908508301,
              "neg_std": 2.0765788555145264,
              "layer": 6
            },
            {
              "accuracy": 1.0,
              "separation": 20.28554630279541,
              "pos_mean": 11.811737060546875,
              "neg_mean": -8.473809242248535,
              "pos_std": 4.576165199279785,
              "neg_std": 2.1223556995391846,
              "layer": 7
            },
            {
              "accuracy": 1.0,
              "separation": 20.606478691101074,
              "pos_mean": 12.086203575134277,
              "neg_mean": -8.520275115966797,
              "pos_std": 4.819287300109863,
              "neg_std": 2.0120601654052734,
              "layer": 8
            },
            {
              "accuracy": 1.0,
              "separation": 20.68310260772705,
              "pos_mean": 12.059209823608398,
              "neg_mean": -8.623892784118652,
              "pos_std": 4.479454040527344,
              "neg_std": 1.9475761651992798,
              "layer": 9
            },
            {
              "accuracy": 1.0,
              "separation": 20.958033561706543,
              "pos_mean": 12.213876724243164,
              "neg_mean": -8.744156837463379,
              "pos_std": 4.535684108734131,
              "neg_std": 1.9799633026123047,
              "layer": 10
            },
            {
              "accuracy": 1.0,
              "separation": 21.331327438354492,
              "pos_mean": 12.352913856506348,
              "neg_mean": -8.978413581848145,
              "pos_std": 4.393656253814697,
              "neg_std": 2.045498847961426,
              "layer": 11
            },
            {
              "accuracy": 1.0,
              "separation": 21.333637237548828,
              "pos_mean": 12.355013847351074,
              "neg_mean": -8.978623390197754,
              "pos_std": 4.285254001617432,
              "neg_std": 1.9801541566848755,
              "layer": 12
            },
            {
              "accuracy": 1.0,
              "separation": 22.144091606140137,
              "pos_mean": 12.790506362915039,
              "neg_mean": -9.353585243225098,
              "pos_std": 4.364027976989746,
              "neg_std": 2.131328582763672,
              "layer": 13
            },
            {
              "accuracy": 1.0,
              "separation": 22.638129234313965,
              "pos_mean": 13.221464157104492,
              "neg_mean": -9.416665077209473,
              "pos_std": 4.585049152374268,
              "neg_std": 2.100287914276123,
              "layer": 14
            },
            {
              "accuracy": 1.0,
              "separation": 23.32382297515869,
              "pos_mean": 13.55907917022705,
              "neg_mean": -9.76474380493164,
              "pos_std": 4.259362697601318,
              "neg_std": 2.2586891651153564,
              "layer": 15
            },
            {
              "accuracy": 1.0,
              "separation": 24.35505962371826,
              "pos_mean": 13.91434383392334,
              "neg_mean": -10.440715789794922,
              "pos_std": 4.503419876098633,
              "neg_std": 2.4652276039123535,
              "layer": 16
            },
            {
              "accuracy": 1.0,
              "separation": 24.663973808288574,
              "pos_mean": 14.277300834655762,
              "neg_mean": -10.386672973632812,
              "pos_std": 4.564506530761719,
              "neg_std": 2.3424508571624756,
              "layer": 17
            },
            {
              "accuracy": 1.0,
              "separation": 25.41071128845215,
              "pos_mean": 14.614629745483398,
              "neg_mean": -10.79608154296875,
              "pos_std": 4.765965938568115,
              "neg_std": 2.556619167327881,
              "layer": 18
            },
            {
              "accuracy": 1.0,
              "separation": 25.59208583831787,
              "pos_mean": 14.291772842407227,
              "neg_mean": -11.300312995910645,
              "pos_std": 4.434935092926025,
              "neg_std": 2.7973875999450684,
              "layer": 19
            },
            {
              "accuracy": 1.0,
              "separation": 27.038125038146973,
              "pos_mean": 15.327459335327148,
              "neg_mean": -11.710665702819824,
              "pos_std": 5.2170329093933105,
              "neg_std": 3.006296157836914,
              "layer": 20
            },
            {
              "accuracy": 1.0,
              "separation": 28.0141658782959,
              "pos_mean": 15.499704360961914,
              "neg_mean": -12.514461517333984,
              "pos_std": 5.196756839752197,
              "neg_std": 3.407555341720581,
              "layer": 21
            },
            {
              "accuracy": 1.0,
              "separation": 27.06470012664795,
              "pos_mean": 15.079107284545898,
              "neg_mean": -11.98559284210205,
              "pos_std": 4.786426544189453,
              "neg_std": 2.8673806190490723,
              "layer": 22
            },
            {
              "accuracy": 1.0,
              "separation": 28.14413833618164,
              "pos_mean": 15.496542930603027,
              "neg_mean": -12.647595405578613,
              "pos_std": 4.577796936035156,
              "neg_std": 3.2259812355041504,
              "layer": 23
            },
            {
              "accuracy": 1.0,
              "separation": 28.474066734313965,
              "pos_mean": 16.0815372467041,
              "neg_mean": -12.392529487609863,
              "pos_std": 4.513683795928955,
              "neg_std": 2.845280170440674,
              "layer": 24
            },
            {
              "accuracy": 1.0,
              "separation": 30.524338722229004,
              "pos_mean": 17.397260665893555,
              "neg_mean": -13.12707805633545,
              "pos_std": 4.909887790679932,
              "neg_std": 3.26823353767395,
              "layer": 25
            }
          ],
          "best_layer": 0,
          "best_accuracy": 1.0,
          "best_separation": 13.248161315917969,
          "avg_accuracy": 1.0
        },
        "ica": {
          "all_layers": []
        },
        "gradient": {
          "all_layers": [
            {
              "accuracy": 0.9282051282051282,
              "separation": 5.36661958694458,
              "pos_mean": 4.5766191482543945,
              "neg_mean": -0.7900004386901855,
              "pos_std": 2.1881957054138184,
              "neg_std": 0.8554439544677734,
              "layer": 0
            },
            {
              "accuracy": 0.9641025641025641,
              "separation": 7.202988386154175,
              "pos_mean": 4.929737567901611,
              "neg_mean": -2.2732508182525635,
              "pos_std": 2.2846896648406982,
              "neg_std": 1.227756142616272,
              "layer": 1
            },
            {
              "accuracy": 0.9743589743589743,
              "separation": 7.821780204772949,
              "pos_mean": 3.121610164642334,
              "neg_mean": -4.700170040130615,
              "pos_std": 2.538555145263672,
              "neg_std": 1.3106616735458374,
              "layer": 2
            },
            {
              "accuracy": 0.8974358974358975,
              "separation": 9.191096305847168,
              "pos_mean": 2.624173641204834,
              "neg_mean": -6.566922664642334,
              "pos_std": 3.0384812355041504,
              "neg_std": 1.492111325263977,
              "layer": 3
            },
            {
              "accuracy": 0.9743589743589743,
              "separation": 10.340949296951294,
              "pos_mean": 6.481923580169678,
              "neg_mean": -3.859025716781616,
              "pos_std": 3.790982484817505,
              "neg_std": 1.4557546377182007,
              "layer": 4
            },
            {
              "accuracy": 0.958974358974359,
              "separation": 11.858133316040039,
              "pos_mean": 5.2189507484436035,
              "neg_mean": -6.6391825675964355,
              "pos_std": 4.280656814575195,
              "neg_std": 1.6481233835220337,
              "layer": 5
            },
            {
              "accuracy": 0.9743589743589743,
              "separation": 12.485978126525879,
              "pos_mean": 9.021143913269043,
              "neg_mean": -3.464834213256836,
              "pos_std": 5.119881629943848,
              "neg_std": 1.5498805046081543,
              "layer": 6
            },
            {
              "accuracy": 0.9641025641025641,
              "separation": 18.175759315490723,
              "pos_mean": 8.563076972961426,
              "neg_mean": -9.612682342529297,
              "pos_std": 6.013030529022217,
              "neg_std": 2.6085760593414307,
              "layer": 7
            },
            {
              "accuracy": 0.9846153846153847,
              "separation": 16.633671283721924,
              "pos_mean": 9.248859405517578,
              "neg_mean": -7.384811878204346,
              "pos_std": 5.373305797576904,
              "neg_std": 2.455629348754883,
              "layer": 8
            },
            {
              "accuracy": 0.9641025641025641,
              "separation": 20.5986590385437,
              "pos_mean": 15.744490623474121,
              "neg_mean": -4.85416841506958,
              "pos_std": 7.2375807762146,
              "neg_std": 2.851409912109375,
              "layer": 9
            },
            {
              "accuracy": 0.958974358974359,
              "separation": 21.12751293182373,
              "pos_mean": 8.502389907836914,
              "neg_mean": -12.625123023986816,
              "pos_std": 7.2311625480651855,
              "neg_std": 2.4207019805908203,
              "layer": 10
            },
            {
              "accuracy": 0.9846153846153847,
              "separation": 24.317157745361328,
              "pos_mean": 15.561810493469238,
              "neg_mean": -8.75534725189209,
              "pos_std": 9.23115062713623,
              "neg_std": 2.750960111618042,
              "layer": 11
            },
            {
              "accuracy": 0.9641025641025641,
              "separation": 27.578170776367188,
              "pos_mean": 12.463334083557129,
              "neg_mean": -15.114836692810059,
              "pos_std": 9.048239707946777,
              "neg_std": 3.247864007949829,
              "layer": 12
            },
            {
              "accuracy": 0.9794871794871794,
              "separation": 29.652522087097168,
              "pos_mean": 17.712852478027344,
              "neg_mean": -11.939669609069824,
              "pos_std": 10.159012794494629,
              "neg_std": 3.5994153022766113,
              "layer": 13
            },
            {
              "accuracy": 0.9846153846153847,
              "separation": 28.089282035827637,
              "pos_mean": 16.93220329284668,
              "neg_mean": -11.157078742980957,
              "pos_std": 9.516997337341309,
              "neg_std": 3.494417428970337,
              "layer": 14
            },
            {
              "accuracy": 0.9846153846153847,
              "separation": 35.53280162811279,
              "pos_mean": 19.924379348754883,
              "neg_mean": -15.60842227935791,
              "pos_std": 11.368739128112793,
              "neg_std": 4.741153240203857,
              "layer": 15
            },
            {
              "accuracy": 0.9897435897435898,
              "separation": 40.53659629821777,
              "pos_mean": 21.268783569335938,
              "neg_mean": -19.267812728881836,
              "pos_std": 11.836605072021484,
              "neg_std": 5.5195722579956055,
              "layer": 16
            },
            {
              "accuracy": 0.9743589743589743,
              "separation": 42.161434173583984,
              "pos_mean": 29.11557388305664,
              "neg_mean": -13.045860290527344,
              "pos_std": 12.492501258850098,
              "neg_std": 5.793822288513184,
              "layer": 17
            },
            {
              "accuracy": 0.9641025641025641,
              "separation": 53.261515617370605,
              "pos_mean": 39.06657409667969,
              "neg_mean": -14.194941520690918,
              "pos_std": 16.49857521057129,
              "neg_std": 7.639264106750488,
              "layer": 18
            },
            {
              "accuracy": 0.9435897435897436,
              "separation": 60.19221878051758,
              "pos_mean": 50.01353454589844,
              "neg_mean": -10.17868423461914,
              "pos_std": 18.767414093017578,
              "neg_std": 8.787023544311523,
              "layer": 19
            },
            {
              "accuracy": 0.9794871794871794,
              "separation": 65.42364311218262,
              "pos_mean": 35.64767837524414,
              "neg_mean": -29.775964736938477,
              "pos_std": 17.58255386352539,
              "neg_std": 10.047430992126465,
              "layer": 20
            },
            {
              "accuracy": 0.9794871794871794,
              "separation": 76.51985549926758,
              "pos_mean": 40.95853042602539,
              "neg_mean": -35.56132507324219,
              "pos_std": 20.366615295410156,
              "neg_std": 12.618610382080078,
              "layer": 21
            },
            {
              "accuracy": 0.9743589743589743,
              "separation": 78.95410537719727,
              "pos_mean": 44.71429443359375,
              "neg_mean": -34.239810943603516,
              "pos_std": 19.375207901000977,
              "neg_std": 12.99339771270752,
              "layer": 22
            },
            {
              "accuracy": 0.958974358974359,
              "separation": 87.0981616973877,
              "pos_mean": 60.5695915222168,
              "neg_mean": -26.5285701751709,
              "pos_std": 20.094030380249023,
              "neg_std": 15.67919635772705,
              "layer": 23
            },
            {
              "accuracy": 0.9743589743589743,
              "separation": 110.66106033325195,
              "pos_mean": 72.9848861694336,
              "neg_mean": -37.67617416381836,
              "pos_std": 27.196672439575195,
              "neg_std": 17.859317779541016,
              "layer": 24
            },
            {
              "accuracy": 0.9743589743589743,
              "separation": 136.2402572631836,
              "pos_mean": 87.38483428955078,
              "neg_mean": -48.85542297363281,
              "pos_std": 31.112146377563477,
              "neg_std": 21.797985076904297,
              "layer": 25
            }
          ],
          "best_layer": 16,
          "best_accuracy": 0.9897435897435898,
          "best_separation": 40.53659629821777,
          "avg_accuracy": 0.9674556213017753
        }
      }
    },
    "inst_nat": {
      "description": "Instruction \u2192 Natural",
      "vector_source": "defensiveness",
      "test_source": "natural",
      "methods": {
        "mean_diff": {
          "all_layers": []
        },
        "probe": {
          "all_layers": []
        },
        "ica": {
          "all_layers": []
        },
        "gradient": {
          "all_layers": []
        }
      }
    },
    "nat_inst": {
      "description": "Natural \u2192 Instruction",
      "vector_source": "defensiveness_natural",
      "test_source": "instruction",
      "methods": {
        "mean_diff": {
          "all_layers": []
        },
        "probe": {
          "all_layers": []
        },
        "ica": {
          "all_layers": []
        },
        "gradient": {
          "all_layers": []
        }
      }
    },
    "nat_nat": {
      "description": "Natural \u2192 Natural",
      "vector_source": "defensiveness_natural",
      "test_source": "natural",
      "methods": {
        "mean_diff": {
          "all_layers": []
        },
        "probe": {
          "all_layers": []
        },
        "ica": {
          "all_layers": []
        },
        "gradient": {
          "all_layers": []
        }
      }
    }
  }
}